CHANGELOG.rst
LICENSE
MANIFEST.in
README.rst
setup.cfg
setup.py
django_reversion_pynamodb.egg-info/PKG-INFO
django_reversion_pynamodb.egg-info/SOURCES.txt
django_reversion_pynamodb.egg-info/dependency_links.txt
django_reversion_pynamodb.egg-info/not-zip-safe
django_reversion_pynamodb.egg-info/requires.txt
django_reversion_pynamodb.egg-info/top_level.txt
docs/admin.rst
docs/api.rst
docs/backends.rst
docs/changelog.rst
docs/commands.rst
docs/common-problems.rst
docs/conf.py
docs/errors.rst
docs/index.rst
docs/middleware.rst
docs/signals.rst
docs/views.rst
docs/_include/admin.rst
docs/_include/create-revision-args.rst
docs/_include/create-revision-atomic.rst
docs/_include/create-revision-manage-manually.rst
docs/_include/create-revision-using.rst
docs/_include/model-db-arg.rst
docs/_include/post-register.rst
docs/_include/signal-args.rst
docs/_include/throws-registration-error.rst
docs/_include/throws-revert-error.rst
docs/_include/throws-revision-error.rst
reversion/__init__.py
reversion/errors.py
reversion/middleware.py
reversion/models.py
reversion/revisions.py
reversion/signals.py
reversion/views.py
reversion/backends/__init__.py
reversion/backends/utils.py
reversion/backends/dynamodb/__init__.py
reversion/backends/dynamodb/app.py
reversion/backends/dynamodb/models.py
reversion/backends/dynamodb/queryset.py
reversion/backends/dynamodb/management/__init__.py
reversion/backends/dynamodb/management/commands/__init__.py
reversion/backends/dynamodb/management/commands/initdynamodbreversion.py
reversion/backends/sql/__init__.py
reversion/backends/sql/admin.py
reversion/backends/sql/app.py
reversion/backends/sql/models.py
reversion/backends/sql/management/__init__.py
reversion/backends/sql/management/commands/__init__.py
reversion/backends/sql/management/commands/createinitialrevisions.py
reversion/backends/sql/management/commands/deleterevisions.py
reversion/backends/sql/migrations/0001_squashed_0004_auto_20160611_1202.py
reversion/backends/sql/migrations/__init__.py
reversion/locale/ar/LC_MESSAGES/django.mo
reversion/locale/ar/LC_MESSAGES/django.po
reversion/locale/cs/LC_MESSAGES/django.mo
reversion/locale/cs/LC_MESSAGES/django.po
reversion/locale/da/LC_MESSAGES/django.mo
reversion/locale/da/LC_MESSAGES/django.po
reversion/locale/de/LC_MESSAGES/django.mo
