Metadata-Version: 2.1
Name: django-reversion-pynamodb
Version: 0.1.6
Summary: An extension to the Django web framework that provides version control for model instances.
Home-page: http://github.com/druids/django-reversion-pynamodb
Author: Dave Hall,Lubos Matl
Author-email: dave@etianen.com, matllubos@gmail.com
License: BSD
Platform: UNKNOWN
Classifier: Development Status :: 5 - Production/Stable
Classifier: Environment :: Web Environment
Classifier: Intended Audience :: Developers
Classifier: License :: OSI Approved :: BSD License
Classifier: Operating System :: OS Independent
Classifier: Programming Language :: Python
Classifier: Programming Language :: Python :: 3.6
Classifier: Programming Language :: Python :: 3.7
Classifier: Programming Language :: Python :: 3.8
Classifier: Framework :: Django
Requires-Python: >=3.6
Provides-Extra: dynamodb
